setup.py
motivate/__init__.py
motivate/me.py
motivate_lizixi.egg-info/PKG-INFO
motivate_lizixi.egg-info/SOURCES.txt
motivate_lizixi.egg-info/dependency_links.txt
motivate_lizixi.egg-info/top_level.txt