Metadata-Version: 1.0
Name: motivate-lizixi
Version: 0.1.2
Summary: a Python moudle to motivate you
Home-page: UNKNOWN
Author: UNKNOWN
Author-email: UNKNOWN
License: UNKNOWN
Platform: UNKNOWN
